ai_inspector/__init__.py
ai_inspector/client.py
ai_inspector/inspector.py
ai_inspector/io_utils.py
ai_inspector/py.typed
ai_inspector/python_utils.py
ai_inspector-0.1.2.dist-info/LICENSE
ai_inspector-0.1.2.dist-info/WHEEL
ai_inspector-0.1.2.dist-info/METADATA
ai_inspector-0.1.2.dist-info/RECORD
