Metadata-Version: 2.1
Name: ai-inspector
Version: 0.1.2
Summary: Inspect your AI models visually, find bugs, give feedback 🕵️‍♀️ 💬
Home-page: https://github.com/Giskard-AI/ai-inspector
License: Apache Software License 2.0
Keywords: Artificial Intelligence,Machine Learning,Quality,MLOps
Author: Giskard AI
Author-email: hello@giskard.ai
Requires-Python: >=3.7.1,<3.8.0
Classifier: Development Status :: 4 - Beta
Classifier: Intended Audience :: Developers
Classifier: Intended Audience :: Science/Research
Classifier: License :: OSI Approved :: Apache Software License
Classifier: License :: Other/Proprietary License
Classifier: Operating System :: OS Independent
Classifier: Programming Language :: Python :: 3
Classifier: Programming Language :: Python :: 3 :: Only
Classifier: Programming Language :: Python :: 3.7
Classifier: Topic :: Scientific/Engineering :: Artificial Intelligence
Requires-Dist: api-client (>=1.3.1,<2.0.0)
Requires-Dist: cloudpickle (>=1.3.0,<1.7.0)
Requires-Dist: importlib_metadata (>=4.5.0,<5.0.0); python_version < "3.8"
Requires-Dist: ipywidgets (>=7.6.3,<8.0.0)
Requires-Dist: jupyter-http-over-ws (>=0.0.8,<0.0.9)
Requires-Dist: numpy (>=1.19.0,<2.0.0)
Requires-Dist: pandas (>=1.0.0,<2.0.0)
Requires-Dist: pydantic (>=1.7.1,<1.9.0)
Requires-Dist: python-dotenv (>=0.17.0,<0.18.0)
Requires-Dist: scikit-learn (>=0.22.0,<0.25.0)
Requires-Dist: types-requests (>=2.25.8,<3.0.0)
Requires-Dist: typing-extensions (>=3.7.4,<4.0.0)
Requires-Dist: zstandard (>=0.15.2,<0.16.0)
Project-URL: Repository, https://github.com/Giskard-AI/ai-inspector
